Metadata-Version: 2.1
Name: streamlit-with-ssl
Version: 1.15.2.1
Summary: The fastest way to build data apps in Python (better with SSL)
Home-page: https://streamlit.io
Author: Snowflake Inc
Author-email: hello@streamlit.io
License: Apache License 2.0
Project-URL: Source Code, https://github.com/streamlit/streamlit
Project-URL: Bug Tracker, https://github.com/streamlit/streamlit/issues
Project-URL: Release notes, https://docs.streamlit.io/library/changelog
Project-URL: Documentation, https://docs.streamlit.io/
Project-URL: Community, https://discuss.streamlit.io/
Project-URL: Twitter, https://twitter.com/streamlit
Classifier: Development Status :: 5 - Production/Stable
Classifier: Environment :: Console
Classifier: Environment :: Web Environment
Classifier: Intended Audience :: Developers
Classifier: Intended Audience :: Science/Research
Classifier: License :: OSI Approved :: Apache Software License
Classifier: Programming Language :: Python :: 3.7
Classifier: Programming Language :: Python :: 3.8
Classifier: Programming Language :: Python :: 3.9
Classifier: Programming Language :: Python :: 3.10
Classifier: Topic :: Database :: Front-Ends
Classifier: Topic :: Office/Business :: Financial :: Spreadsheet
Classifier: Topic :: Scientific/Engineering :: Information Analysis
Classifier: Topic :: Scientific/Engineering :: Visualization
Classifier: Topic :: Software Development :: Libraries :: Application Frameworks
Classifier: Topic :: Software Development :: Widget Sets
Requires-Python: >=3.7, !=3.9.7
Requires-Dist: altair (>=3.2.0)
Requires-Dist: blinker (>=1.0.0)
Requires-Dist: cachetools (>=4.0)
Requires-Dist: click (>=7.0)
Requires-Dist: importlib-metadata (>=1.4)
Requires-Dist: numpy
Requires-Dist: packaging (>=14.1)
Requires-Dist: pandas (>=0.21.0)
Requires-Dist: pillow (>=6.2.0)
Requires-Dist: protobuf (<4,>=3.12)
Requires-Dist: pyarrow (>=4.0)
Requires-Dist: pympler (>=0.9)
Requires-Dist: python-dateutil
Requires-Dist: requests (>=2.4)
Requires-Dist: rich (>=10.11.0)
Requires-Dist: semver
Requires-Dist: toml
Requires-Dist: typing-extensions (>=3.10.0.0)
Requires-Dist: tzlocal (>=1.1)
Requires-Dist: validators (>=0.2)
Requires-Dist: gitpython (!=3.1.19)
Requires-Dist: pydeck (>=0.1.dev5)
Requires-Dist: tornado (>=5.0)
Requires-Dist: watchdog ; platform_system != "Darwin"
Provides-Extra: snowflake
Requires-Dist: snowflake-snowpark-python ; (python_version == "3.8") and extra == 'snowflake'
